{
    "menu":"Menu",
    "yummylist":"Yummy List",
    "brunches":"Branches",
    "orderslist":"My Order",
    "error":"sorry something went wrong",
    "noti_thanks": "thanks, Item addded to cart",
    "noti_addcart": "please use plus/minus to change Quantity",
    "errorMail" :"please enter a valid email address",
    "loginErrorText" : "username or password not valid",
    "loginErrorTitle" : "please try again",
    "errorPhone":"please enter a valid Phone Number",
    "errorPassword":"8 to 20 characters which contain only characters, numeric digits",
    "errorTime": "Please Enter Time",
    "errorDate": "Please Enter Date",
    "errorText" : "Please Enter Value",
    "pro_updated":"Thanks, Your profile information has been updated ",
    "plc_updated":"Thanks, Your place information has been updated ",
    "plc_error":"sorry something went wrong",
    "brch_req":"Some Fields Can not be blank ",
    "brch_error":"sorry, something went wrong please try again",
    "ord_done":"Thanks, your order will be ready soon<br> your order number",
    "yum_con":"sorry, no Items found . please see our menu and Choose your yummy foods ",
    "yum_lin":"Our Menu",
    "monthnames" :  {
        "January" :"January",
        "February":"February",
        "March":"March",
        "April":"April",
        "May":"May",
        "June":"June",
        "July":"July",
        "August":"August",
        "September":"September",
        "October":"October",
        "November":"November",
        "December":"December"
    } ,
    "daysNames":  {
        "Sunday":"Sunday",
        "Monday":"Monday",
        "Tuesday":"Tuesday",
        "Wednesday": "Wednesday",
        "Thursday":"Thursday",
        "Friday" :"Friday",
        "Saturday":"Saturday"
    }
}
